LICENSE
MANIFEST.in
README.rst
setup.py
bin/slurp
slurp/__init__.py
slurp/block.py
slurp/channel.py
slurp/config.py
slurp/form.py
slurp/settings.py
slurp/sink.py
slurp/source.py
slurp.egg-info/PKG-INFO
slurp.egg-info/SOURCES.txt
slurp.egg-info/dependency_links.txt
slurp.egg-info/requires.txt
slurp.egg-info/top_level.txt
slurp/ext/__init__.py
slurp/ext/elasticsearch.py
slurp/ext/email.py
slurp/ext/sentry.py