Metadata-Version: 1.1
Name: slurp
Version: 0.6.2
Summary: Slurper
Home-page: https://github.com/bninja/slurp
Author: slurp
Author-email: egon@gb.com
License: UNKNOWN
Platform: UNKNOWN
Classifier: Development Status :: 4 - Beta
Classifier: Intended Audience :: Developers
Classifier: Natural Language :: English
Classifier: License :: OSI Approved :: ISC License (ISCL)
Classifier: Programming Language :: Python
Classifier: Programming Language :: Python :: 2.7
